[
  {
    "id": "01",
    "desc": "A snow-covered tree in the middle of the night"
  },
  {
    "id": "02",
    "desc": "White leaves"
  },
  {
    "id": "category/01",
    "desc": "White snow flakes"
  },
  {
    "id": "category/02",
    "desc": "White and brown bokeh lights"
  },
  {
    "id": "https://images.unsplash.com/photo-1522725539107-ed9cef5284d1",
    "desc": "Snow-covered pine tree during daytime"
  },
  {
    "id": "https://images.unsplash.com/photo-1612476177007-a36dc9e6d7a3",
    "desc": "Shallow-focus photography of black and brown camera"
  },
  {
    "id": "https://images.unsplash.com/photo-1579839782910-8c7761c3680d",
    "desc": "Green trees on snow-covered ground during daytime"
  },
  {
    "id": "https://images.unsplash.com/photo-1510798831971-661eb04b3739",
    "desc": "Wooden house near pine trees and pond coated with snow during daytime"
  },
  {
    "id": "https://images.unsplash.com/photo-1742278508115-8d73f8909795",
    "desc": "Wooden cabin stands in the snowy field"
  },
  {
    "id": "https://images.unsplash.com/photo-1609186556802-d30ef6426f53",
    "desc": "Black-and-white street light"
  },
  {
    "id": "https://images.unsplash.com/photo-1580948799645-a77e022a5cf3",
    "desc": "People riding on cable cars during daytime"
  },
  {
    "id": "https://images.unsplash.com/photo-1513016805932-501981d32562",
    "desc": "Person holding umbrella near streetlight and trees at daytime"
  },
  {
    "id": "https://images.unsplash.com/photo-1480792804297-cd19a6412623",
    "desc": "Selective-focus photography of white and pink-petaled flowers"
  },
  {
    "id": "https://images.unsplash.com/photo-1613234509662-8d377c484a43",
    "desc": "Green pine tree covered with snow"
  },
  {
    "id": "https://images.unsplash.com/photo-1514102298652-725a91d32459",
    "desc": "White-and-red cable train during winter"
  },
  {
    "id": "https://images.unsplash.com/photo-1482331336918-c80fab6c90f2",
    "desc": "Shallow-focus photography of pine-cone"
  },
  {
    "id": "https://images.unsplash.com/photo-1609187103682-7ddf1d1da0e5",
    "desc": "Green pine tree during daytime"
  },
  {
    "id": "https://images.unsplash.com/photo-1517719689-329a917e7ba6",
    "desc": "House in between trees and dock under gray sky"
  },
  {
    "id": "https://images.unsplash.com/photo-1521319411283-5132e77195de",
    "desc": "Brown concrete building near mountain covered with snows at daytime"
  },
  {
    "id": "https://images.unsplash.com/photo-1548704806-0c20f7ea6474",
    "desc": "Brown wooden house near green leafed trees"
  },
  {
    "id": "https://images.unsplash.com/photo-1582492610422-2a68cd937373",
    "desc": "Brown wooden house near trees during daytime"
  },
  {
    "id": "https://images.unsplash.com/photo-1649884771334-f1b869891786",
    "desc": "Snow covered forest filled with lots of trees"
  },
  {
    "id": "https://images.unsplash.com/photo-1613063300761-cc8072e230f0",
    "desc": "Green pine tree covered with snow"
  },
  {
    "id": "https://images.unsplash.com/photo-1542601098-8fc114e148e2",
    "desc": "Black-and-white photo of snow falling"
  },
  {
    "id": "https://images.unsplash.com/photo-1705259633593-541809383836",
    "desc": "A pine tree covered in snow in a forest"
  },
  {
    "id": "https://images.unsplash.com/photo-1615465056436-5d24422a1e16",
    "desc": "Green pine tree covered with snow"
  },
  {
    "id": "https://images.unsplash.com/photo-1703179007975-6aeea846f663",
    "desc": "Christmas ornament hanging from a Christmas tree"
  },
  {
    "id": "https://images.unsplash.com/photo-1638399882338-229e2652c7c8",
    "desc": "A toy car covered in snow next to a Christmas tree"
  },
  {
    "id": "https://images.unsplash.com/photo-1671759680267-2fc02674525a",
    "desc": "Branch of a pine covered in snow"
  },
  {
    "id": "https://images.unsplash.com/photo-1613291391434-759c95f779ef",
    "desc": "Snow-covered pine tree during daytime"
  },
  {
    "id": "https://images.unsplash.com/photo-1612442832703-3be6a48cfdd5",
    "desc": "White wooden house covered with snow"
  },
  {
    "id": "https://images.unsplash.com/photo-1491817570045-8252ee149361",
    "desc": "Selective-focus photography of tree"
  },
  {
    "id": "https://images.unsplash.com/photo-1671759680397-fb9f3b4cf3b4",
    "desc": "Close-up of a pine tree with snow on it"
  },
  {
    "id": "https://images.unsplash.com/photo-1703179040740-fcd88a700b3a",
    "desc": "Close-up of a Christmas tree with ornaments on it"
  },
  {
    "id": "https://images.unsplash.com/photo-1514571948039-d3cb9e8f9750",
    "desc": "White dog standing on snow field beside pine tree"
  }
]
